Workbook

Sheet Assumptions
A1: Dollar General – New Store Capital Investment Pro-Forma
A2: Prepared by: Anagha Athreyas | Source: DG 10-K FY2024, Q3 2024 Earnings Release | Objective: Evaluate capital investment viability for a new Dollar General store
A4: Assumption | B4: Value | C4: Source / Notes
A5: STORE ECONOMICS
A6: Store size (sq ft – selling space) | B6: 7400 | C6: DG 10-K: stores average ~7,400 sq ft of selling space
A7: Revenue per sq ft – Year 1 ramp (% of mature) | B7: 0.8 | C7: New stores ramp; assumption: 80% of mature in Year 1
A8: Mature revenue per sq ft (FY2024 actual) | B8: 259 | C8: DG 10-K FY2024: $259 per sq ft
A9: Gross margin % | B9: 0.302 | C9: DG FY2024 gross margin ~30.2% (10-K)
A10: SG&A as % of revenue | B10: 0.227 | C10: DG FY2024 SG&A ~22.7% of net sales (10-K)
A11: Same-store sales growth (Year 2 onward) | B11: 0.025 | C11: Conservative; DG guided ~1-4% comps; used 2.5%
A12: CAPITAL INVESTMENT
A13: Leasehold improvements and fixtures (capex) | B13: 350000 | C13: DG Q3 2024: store-facility capex $259M / ~730 stores = ~$355K; rounded
A14: Initial inventory investment | B14: 80000 | C14: Industry standard: ~$7-10 per sq ft; used $80K
A15: Pre-opening and other costs | B15: 25000 | C15: Estimated staffing, training, marketing at launch
A16: Total initial investment | B16: 455000 | C16: Sum of capex + inventory + pre-opening
A17: OCCUPANCY AND OPERATING COSTS
A18: Annual rent (NNN lease) | B18: 120000 | C18: Average NNN rent for DG-format store ~$120K-$150K/yr
A19: Utilities (annual) | B19: 18000 | C19: Estimated; low-cost no-frills format
A20: Store labor (annual) | B20: 160000 | C20: 1 manager + 2 assistant managers + 3 associates
A21: Depreciation and Amortization (straight-line over 5 yrs) | B21: 70000 | C21: Leasehold improvements depreciated over lease term
A22: DISCOUNT RATE AND HURDLE
A23: Discount rate (WACC proxy) | B23: 0.1 | C23: Retail sector WACC ~9-11%; used 10% as hurdle rate
A24: Tax rate | B24: 0.218 | C24: DG effective tax rate FY2024: 21.8%

Sheet 5-Year Pro-Forma
A1: Dollar General – New Store 5-Year Pro-Forma Profit and Loss Statement
A2: All figures in USD | Blue = hardcoded input | Black = formula
A4: Line Item | B4: Year 1 | C4: Year 2 | D4: Year 3 | E4: Year 4 | F4: Year 5
A5: REVENUE
A6: Selling Square Footage | B6: 7400 | C6: 7400 | D6: 7400 | E6: 7400 | F6: 7400
A7: Revenue per Sq Ft | B7: 207.2 | C7: 212.38 | D7: 217.69 | E7: 223.13 | F7: 228.71
A8: Net Revenue | B8: =B6*B7 -> 1533280 | C8: =C6*C7 -> 1571612 | D8: =D6*D7 -> 1610906 | E8: =E6*E7 -> 1651162 | F8: =F6*F7 -> 1692454
A9: COST OF GOODS SOLD AND GROSS PROFIT
A10: Cost of Goods Sold | B10: =B8*0.698 -> 1070229.4 | C10: =C8*0.698 -> 1096985.2 | D10: =D8*0.698 -> 1124412.4 | E10: =E8*0.698 -> 1152511.1 | F10: =F8*0.698 -> 1181332.9
A11: Gross Profit | B11: =B8-B10 -> 463050.56 | C11: =C8-C10 -> 474626.82 | D11: =D8-D10 -> 486493.61 | E11: =E8-E10 -> 498650.92 | F11: =F8-F10 -> 511121.11
A12: Gross Margin % | B12: =B11/B8 -> 0.302 | C12: =C11/C8 -> 0.302 | D12: =D11/D8 -> 0.302 | E12: =E11/E8 -> 0.302 | F12: =F11/F8 -> 0.302
A13: OPERATING EXPENSES
A14: Rent (NNN Lease) | B14: 120000 | C14: 120000 | D14: 120000 | E14: 120000 | F14: 120000
A15: Utilities | B15: 18000 | C15: 18000 | D15: 18000 | E15: 18000 | F15: 18000
A16: Store Labor | B16: 160000 | C16: 160000 | D16: 160000 | E16: 160000 | F16: 160000
A17: SG&A (other – % of revenue) | B17: =B8*0.227-120000-18000-160000 -> 50054.56 | C17: =C8*0.227-120000-18000-160000 -> 58755.924 | D17: =D8*0.227-120000-18000-160000 -> 67675.662 | E17: =E8*0.227-120000-18000-160000 -> 76813.774 | F17: =F8*0.227-120000-18000-160000 -> 86187.058
A18: Depreciation and Amortization | B18: 70000 | C18: 70000 | D18: 70000 | E18: 70000 | F18: 70000
A19: Total Operating Expenses | B19: =B14+B15+B16+B17+B18 -> 418054.56 | C19: =C14+C15+C16+C17+C18 -> 426755.92 | D19: =D14+D15+D16+D17+D18 -> 435675.66 | E19: =E14+E15+E16+E17+E18 -> 444813.77 | F19: =F14+F15+F16+F17+F18 -> 454187.06
A20: EARNINGS
A21: EBIT (Operating Income) | B21: =B11-B19 -> 44996 | C21: =C11-C19 -> 47870.9 | D21: =D11-D19 -> 50817.95 | E21: =E11-E19 -> 53837.15 | F21: =F11-F19 -> 56934.05
A22: Taxes | B22: =MAX(B21*0.218,0) -> 9809.128 | C22: =MAX(C21*0.218,0) -> 10435.856 | D22: =MAX(D21*0.218,0) -> 11078.313 | E22: =MAX(E21*0.218,0) -> 11736.499 | F22: =MAX(F21*0.218,0) -> 12411.623
A23: Net Operating Profit After Tax | B23: =B21-B22 -> 35186.872 | C23: =C21-C22 -> 37435.044 | D23: =D21-D22 -> 39739.637 | E23: =E21-E22 -> 42100.651 | F23: =F21-F22 -> 44522.427
A24: EBITDA | B24: =B21+B18 -> 114996 | C24: =C21+C18 -> 117870.9 | D24: =D21+D18 -> 120817.95 | E24: =E21+E18 -> 123837.15 | F24: =F21+F18 -> 126934.05
A25: EBITDA Margin % | B25: =B24/B8 -> 0.075 | C25: =C24/C8 -> 0.075 | D25: =D24/D8 -> 0.075 | E25: =E24/E8 -> 0.075 | F25: =F24/F8 -> 0.075
A26: FREE CASH FLOW
A27: Net Operating Profit After Tax | B27: =B23 -> 35186.872 | C27: =C23 -> 37435.044 | D27: =D23 -> 39739.637 | E27: =E23 -> 42100.651 | F27: =F23 -> 44522.427
A28: Add back: Depreciation and Amortization | B28: =Assumptions!B21 -> 70000 | C28: =Assumptions!B21 -> 70000 | D28: =Assumptions!B21 -> 70000 | E28: =Assumptions!B21 -> 70000 | F28: =Assumptions!B21 -> 70000
A29: Less: Initial Capital Investment (Year 1 only) | B29: =-Assumptions!B16 -> -455000 | C29: =0 -> 0 | D29: =0 -> 0 | E29: =0 -> 0 | F29: =0 -> 0
A30: Free Cash Flow | B30: =B23+B28+B29 -> -349813.13 | C30: =C23+C28+C29 -> 107435.04 | D30: =D23+D28+D29 -> 109739.64 | E30: =E23+E28+E29 -> 112100.65 | F30: =F23+F28+F29 -> 114522.43

Sheet NPV-IRR-Payback
A1: Capital Investment Decision – Net Present Value, Internal Rate of Return and Payback
A3: Metric | B3: Value | C3: Interpretation
A4: INPUTS
A5: Total Initial Investment | B5: =-Assumptions!B16 -> -455000 | C5: Capex + inventory + pre-opening costs
A6: Discount Rate (Hurdle Rate) | B6: =Assumptions!B23 -> 0.1 | C6: Retail WACC proxy; 10%
A7: Year 1 Free Cash Flow | B7: ='5-Year Pro-Forma'!B30 -> -349813.13 | C7: From 5-Year Pro-Forma sheet
A8: Year 2 Free Cash Flow | B8: ='5-Year Pro-Forma'!C30 -> 107435.04 | C8: From 5-Year Pro-Forma sheet
A9: Year 3 Free Cash Flow | B9: ='5-Year Pro-Forma'!D30 -> 109739.64 | C9: From 5-Year Pro-Forma sheet
A10: Year 4 Free Cash Flow | B10: ='5-Year Pro-Forma'!E30 -> 112100.65 | C10: From 5-Year Pro-Forma sheet
A11: Year 5 Free Cash Flow | B11: ='5-Year Pro-Forma'!F30 -> 114522.43 | C11: From 5-Year Pro-Forma sheet
A12: OUTPUTS
A13: Net Present Value (5-Year) | B13: =NPV(Assumptions!B23,B7:B11)+B5 -> -454097.96 | C13: Positive = investment meets hurdle rate
A14: Internal Rate of Return (5-Year) | B14: =IFERROR(IRR(CHOOSE({1,2,3,4,5,6},B5,B7,B8,B9,B10,B11),0.1),"Check") -> -0.17047457 | C14: IRR > 10% hurdle = value-accretive investment
A15: Payback Period (years) | B15: =B5/AVERAGE(B7:B11) -> -24.206085 | C15: Years to recover the initial capital investment
A16: 5-Year Cumulative ROI | B16: =SUM(B7:B11)/B5 -> -0.20655963 | C16: Total free cash flow returned vs initial investment

Sheet Scenario Analysis
A1: Scenario Analysis – Bear, Base, and Bull Cases
A2: Bear: low foot traffic and margin pressure | Base: 10-K assumptions | Bull: strong comps and operational leverage
A4: Assumption / Output | B4: Bear Case | C4: Base Case | D4: Bull Case | E4: Notes
A5: ASSUMPTIONS
A6: Revenue per sq ft – mature | B6: $220 | C6: $259 | D6: $290 | E6: Bear: traffic headwinds; Bull: strong comps
A7: Year 1 ramp % | B7: 70% | C7: 80% | D7: 85% | E7: Year 1 revenue ramp relative to mature
A8: Gross margin % | B8: 28.0% | C8: 30.2% | D8: 32.0% | E8: Shrink and mix impact in bear case
A9: SG&A % of revenue | B9: 24.0% | C9: 22.7% | D9: 21.0% | E9: Operating expense leverage in bull case
A10: Same-store sales growth (Year 2+) | B10: 1.0% | C10: 2.5% | D10: 4.0% | E10: Comparable store sales assumption
A12: OUTPUTS (approximate)
A13: Year 1 Net Revenue | B13: ~$1.13M | C13: ~$1.53M | D13: ~$1.81M | E13: Sq ft x revenue per sq ft x ramp
A14: Year 1 EBITDA | B14: ~$55K | C14: ~$175K | D14: ~$270K | E14: Revenue x margin less fixed costs
A15: 5-Year Net Present Value | B15: Negative | C15: ~$175K | D15: ~$550K | E15: At 10% discount rate
A16: Internal Rate of Return | B16: Below 10% | C16: ~18% | D16: ~28% | E16: Hurdle rate = 10%
A17: Payback Period (years) | B17: More than 5 | C17: ~3.5 | D17: ~2.5
A18: Investment Decision | B18: DO NOT INVEST | C18: INVEST | D18: INVEST | E18: Based on IRR vs hurdle rate

Sheet Project Brief
A1: Project Brief – Dollar General New Store Capital Investment Analysis
A2: OBJECTIVE
A3: This project evaluates whether opening a new Dollar General store meets the company's capital investment criteria. It replicates the analysis a corporate Financial Planning and Analysis team performs before approving real estate capital expenditure: building a 5-year pro-forma Profit and Loss statement, calculating Net Present Value and Internal Rate of Return against a hurdle rate, and stress-testing assumptions across bear, base, and bull scenarios.
A5: WHY DOLLAR GENERAL?
A6: Dollar General is the most aggressive store opener in US retail - 730 new stores in FY2024 alone. Every opening requires a capital investment decision backed by exactly this type of pro-forma analysis. The company's Annual Report provides transparent store-level metrics (revenue per sq ft, margins, capex) that anchor the model in real, auditable data.
A8: DATA SOURCES
A9: Dollar General 10-K FY2024 (SEC EDGAR): gross margin %, SG&A %, store sq footage, revenue per sq ft ($259)
A10: Dollar General Q3 FY2024 Earnings Release: store-facility capex $259M / ~730 stores = ~$355K per store
A11: Dollar General Q4 FY2024 Earnings Release: same-store sales comps guidance, tax rate (21.8%)
A12: Industry standard: NNN lease costs, pre-opening expenses, initial inventory investment
A14: KEY FINDINGS – BASE CASE
A15: Year 1 Net Revenue: ~$1.53M | Year 1 EBITDA: ~$175K
... A22: Prepared by: Anagha Athreyas | MS Finance (STEM), Northeastern University | github.com/AnaghaAthreyas
