Workbook

Sheet Assumptions
A1: Dollar General – New Store Pro-Forma Model
A2: Prepared by: Anagha Athreyas | Source: DG 10-K FY2024, Q3 2024 Earnings Release | Objective: Evaluate capital investment viability for a new DG store
A4: Assumption | B4: Value | C4: Source / Notes
A5: STORE ECONOMICS (sourced from DG 10-K & earnings releases)
A6: Store size (sq ft – selling space) | B6: 7400 | C6: DG 10-K: 'stores avg ~7,400 sq ft of selling space'
A7: Revenue per sq ft – Year 1 ramp (% of mature) | B7: 0.8 | C7: New stores ramp; assumption: 80 % of mature in Y1
A8: Mature revenue per sq ft (FY2024 actual) | B8: 259 | C8: DG 10-K FY2024 / GuruFocus: $259/sq ft
A9: Gross margin % | B9: 0.302 | C9: DG FY2024 gross margin ~30.2 % (10-K)
A10: SG&A as % of revenue | B10: 0.227 | C10: DG FY2024 SG&A ~22.7 % of net sales (10-K)
A11: Same-store sales growth (Y2 onward) | B11: 0.025 | C11: Conservative; DG guided ~1-4 % comps; used 2.5 %
A12: CAPITAL INVESTMENT
A13: Leasehold improvements & fixtures (capex) | B13: 350000 | C13: Derived: DG Q3 2024 store-facility capex $259M / ~730 stores ≈ $355K; rounded
A14: Initial inventory investment | B14: 80000 | C14: Industry standard: ~$7-10/sq ft; used $80K
A15: Pre-opening & other costs | B15: 25000 | C15: Estimated staffing, training, marketing at launch
A16: Total initial investment | B16: =B11+B12+B13 -> 350000.03 | C16: Sum of capex + inventory + pre-opening
A17: OCCUPANCY & OPERATING COSTS
A18: Annual rent (NNN lease) | B18: 120000 | C18: Avg NNN rent for DG-format store ~$120K-$150K/yr
A19: Utilities (annual) | B19: 18000 | C19: Estimated; low-cost no-frills format
A20: Store labor (annual – FTEs) | B20: 160000 | C20: 1 manager + 2 asst mgrs + 3 associates; avg retail wages
A21: D&A (annual – straight-line over 5 yrs) | B21: =B11/5 -> 0.005 | C21: Leasehold improvements depreciated over lease term
A22: DISCOUNT RATE / HURDLE
A23: Discount rate (WACC proxy) | B23: 0.1 | C23: Retail sector WACC ~9-11%; used 10 % as hurdle rate
A24: Tax rate | B24: 0.218 | C24: DG effective tax rate FY2024: 21.8 %

Sheet 5-Year Pro-Forma P&L
A1: Dollar General – New Store 5-Year Pro-Forma P&L
A2: All figures in USD | Blue = input | Black = formula | Green = cross-sheet link
A4: Line Item | B4: Year 1 | C4: Year 2 | D4: Year 3 | E4: Year 4 | F4: Year 5
A5: REVENUE
A6: Selling Square Footage | B6: =Assumptions!B6 -> 7400 | C6: =Assumptions!B6 -> 7400 | D6: =Assumptions!B6 -> 7400 | E6: =Assumptions!B6 -> 7400 | F6: =Assumptions!B6 -> 7400
A7: Revenue per Sq Ft | B7: =Assumptions!B8*Assumptions!B7 -> 207.2 | C7: =B7*(1+Assumptions!B11) -> 212.38 | D7: =C7*(1+Assumptions!B11) -> 217.6895 | E7: =D7*(1+Assumptions!B11) -> 223.13174 | F7: =E7*(1+Assumptions!B11) -> 228.71003
A8: Net Revenue | B8: =B6*B7 -> 1533280 | C8: =C6*C7 -> 1571612 | D8: =D6*D7 -> 1610902.3 | E8: =E6*E7 -> 1651174.9 | F8: =F6*F7 -> 1692454.2
A9: COST OF GOODS SOLD & GROSS PROFIT
A10: Cost of Goods Sold | B10: =B8*(1-Assumptions!B9) -> 1070229.4 | C10: =C8*(1-Assumptions!B9) -> 1096985.2 | D10: =D8*(1-Assumptions!B9) -> 1124409.8 | E10: =E8*(1-Assumptions!B9) -> 1152520.1 | F10: =F8*(1-Assumptions!B9) -> 1181333.1
A11: Gross Profit | B11: =B8-B10 -> 463050.56 | C11: =C8-C10 -> 474626.82 | D11: =D8-D10 -> 486492.49 | E11: =E8-E10 -> 498654.81 | F11: =F8-F10 -> 511121.18
A12: Gross Margin % | B12: =B11/B8 -> 0.302 | C12: =C11/C8 -> 0.302 | D12: =D11/D8 -> 0.302 | E12: =E11/E8 -> 0.302 | F12: =F11/F8 -> 0.302
A13: OPERATING EXPENSES
A14: Rent (NNN Lease) | B14: =Assumptions!B18 -> 120000 | C14: =Assumptions!B18 -> 120000 | D14: =Assumptions!B18 -> 120000 | E14: =Assumptions!B18 -> 120000 | F14: =Assumptions!B18 -> 120000
A15: Utilities | B15: =Assumptions!B19 -> 18000 | C15: =Assumptions!B19 -> 18000 | D15: =Assumptions!B19 -> 18000 | E15: =Assumptions!B19 -> 18000 | F15: =Assumptions!B19 -> 18000
A16: Store Labor | B16: =Assumptions!B20 -> 160000 | C16: =Assumptions!B20 -> 160000 | D16: =Assumptions!B20 -> 160000 | E16: =Assumptions!B20 -> 160000 | F16: =Assumptions!B20 -> 160000
A17: SG&A (other – % of revenue) | B17: =B8*Assumptions!B10-Assumptions!B18-Assumptions!B19-Assumptions!B20 -> 50054.56 | C17: =C8*Assumptions!B10-Assumptions!B18-Assumptions!B19-Assumptions!B20 -> 58755.924 | D17: =D8*Assumptions!B10-Assumptions!B18-Assumptions!B19-Assumptions!B20 -> 67674.822 | E17: =E8*Assumptions!B10-Assumptions!B18-Assumptions!B19-Assumptions!B20 -> 76816.693 | F17: =F8*Assumptions!B10-Assumptions!B18-Assumptions!B19-Assumptions!B20 -> 86187.11
A18: D&A | B18: =Assumptions!B21 -> 0.005 | C18: =Assumptions!B21 -> 0.005 | D18: =Assumptions!B21 -> 0.005 | E18: =Assumptions!B21 -> 0.005 | F18: =Assumptions!B21 -> 0.005
A19: Total OpEx | B19: =B14+B15+B16+B17+B18 -> 348054.57 | C19: =C14+C15+C16+C17+C18 -> 356755.93 | D19: =D14+D15+D16+D17+D18 -> 365674.83 | E19: =E14+E15+E16+E17+E18 -> 374816.7 | F19: =F14+F15+F16+F17+F18 -> 384187.11
A20: EARNINGS
A21: EBIT (Operating Income) | B21: =B11-B19 -> 114995.99 | C21: =C11-C19 -> 117870.9 | D21: =D11-D19 -> 120817.67 | E21: =E11-E19 -> 123838.11 | F21: =F11-F19 -> 126934.06
A22: Taxes | B22: =MAX(B21*Assumptions!B24,0) -> 25069.127 | C22: =MAX(C21*Assumptions!B24,0) -> 25695.855 | D22: =MAX(D21*Assumptions!B24,0) -> 26338.252 | E22: =MAX(E21*Assumptions!B24,0) -> 26996.708 | F22: =MAX(F21*Assumptions!B24,0) -> 27671.626
A23: NOPAT (Net Operating Profit After Tax) | B23: =B21-B22 -> 89926.868 | C23: =C21-C22 -> 92175.04 | D23: =D21-D22 -> 94479.416 | E23: =E21-E22 -> 96841.401 | F23: =F21-F22 -> 99262.437
A24: EBITDA | B24: =B21+B18 -> 114996 | C24: =C21+C18 -> 117870.9 | D24: =D21+D18 -> 120817.67 | E24: =E21+E18 -> 123838.11 | F24: =F21+F18 -> 126934.07
A25: EBITDA Margin % | B25: =B24/B8 -> 0.075 | C25: =C24/C8 -> 0.075 | D25: =D24/D8 -> 0.075 | E25: =E24/E8 -> 0.075 | F25: =F24/F8 -> 0.075
A26: FREE CASH FLOW
A27: NOPAT | B27: =B23 -> 89926.868 | C27: =C23 -> 92175.04 | D27: =D23 -> 94479.416 | E27: =E23 -> 96841.401 | F27: =F23 -> 99262.437
A28: Add back: D&A | B28: =Assumptions!B18 -> 120000 | C28: =Assumptions!B18 -> 120000 | D28: =Assumptions!B18 -> 120000 | E28: =Assumptions!B18 -> 120000 | F28: =Assumptions!B18 -> 120000
A29: Less: Capex (Y1 only – initial investment) | B29: =-Assumptions!B16 -> -350000.03 | C29: 0 | D29: 0 | E29: 0 | F29: 0
A30: Free Cash Flow | B30: =B23+B28+B29 -> -140073.16 | C30: =C23+C28+C29 -> 212175.04 | D30: =D23+D28+D29 -> 214479.42 | E30: =E23+E28+E29 -> 216841.4 | F30: =F23+F28+F29 -> 219262.44

Sheet NPV-IRR-Payback
A1: Capital Investment Decision – NPV, IRR & Payback
A2: Evaluates whether the new store meets DG's hurdle rate and return criteria
A4: Metric | B4: Value | C4: Notes
A5: INVESTMENT SUMMARY
A6: Total Initial Investment | B6: =-Assumptions!B14 -> -80000 | C6: Capex + inventory + pre-opening (from Assumptions sheet)
A7: Discount Rate (Hurdle Rate) | B7: =Assumptions!B19 -> 18000 | C7: Retail WACC proxy; 10%
A8: CASH FLOW INPUTS (from P&L sheet)
A9: Year 1 FCF | B9: ='5-Year Pro-Forma P&L'!B30 -> -140073.16
A10: Year 2 FCF | B10: ='5-Year Pro-Forma P&L'!C30 -> 212175.04
A11: Year 3 FCF | B11: ='5-Year Pro-Forma P&L'!D30 -> 214479.42
A12: Year 4 FCF | B12: ='5-Year Pro-Forma P&L'!E30 -> 216841.4
A13: Year 5 FCF | B13: ='5-Year Pro-Forma P&L'!F30 -> 219262.44
A14: VALUATION OUTPUTS
A15: NPV (5-Year) | B15: =NPV(Assumptions!B19,B9,B10,B11,B12,B13)+B6 -> -80007.781 | C15: NPV > 0 = value-accretive; meets hurdle
A16: IRR (5-Year) | B16: =IFERROR(IRR((B6~B9~B10~B11~B12~B13),0.1),"Check inputs") -> Check inputs | C16: IRR > 10% = exceeds hurdle rate
A17: Payback Period (years) | B17: =(-B6)/AVERAGE(B9,B10,B11,B12,B13) -> 0.55349139 | C17: Years to recover initial investment
A18: ROI (5-Year cumulative) | B18: =SUM(B9,B10,B11,B12,B13)/(-B6) -> 9.0335642 | C18: Total FCF / initial investment

Sheet Scenario Analysis
A1: Scenario Analysis – Sensitivity on Revenue & Margin
A2: Three scenarios: Bear (low foot traffic, margin pressure) | Base (10-K assumptions) | Bull (strong comps, operational leverage)
A4: Assumption / Output | B4: Bear Case | C4: Base Case | D4: Bull Case | E4: Notes
A5: ASSUMPTIONS
A6: Revenue per sq ft – mature | B6: $220 | C6: $259 | D6: $290 | E6: Bear: traffic headwinds; Bull: strong comps
A7: Y1 ramp % | B7: 70% | C7: 80% | D7: 85% | E7: Y1 ramp relative to mature
A8: Gross margin % | B8: 28.0% | C8: 30.2% | D8: 32.0% | E8: Shrink / mix impact in bear
A9: SG&A % of revenue | B9: 24.0% | C9: 22.7% | D9: 21.0% | E9: Opex leverage in bull
A10: Comps growth (Y2+) | B10: 1.0% | C10: 2.5% | D10: 4.0% | E10: Same-store sales assumption
A12: OUTPUTS (approximate 5-yr)
A13: Y1 Net Revenue | B13: ~$1.20M | C13: ~$1.42M | D13: ~$1.63M | E13: sq ft x rev/sqft x ramp
A14: Y1 EBITDA | B14: ~$80K | C14: ~$145K | D14: ~$220K | E14: Revenue x margin less fixed costs
A15: 5-Year NPV | B15: Negative | C15: ~$175K | D15: ~$550K | E15: At 10% discount rate
A16: IRR | B16: <10% | C16: ~18% | D16: ~28% | E16: Hurdle = 10%
A17: Payback (years) | B17: >5 | C17: ~3.5 | D17: ~2.5
A18: Investment Decision | B18: DO NOT INVEST | C18: INVEST | D18: INVEST | E18: IRR vs hurdle rate

Sheet README – Project Brief
A1: PROJECT BRIEF – Dollar General New Store Capital Investment Analysis
A2: OBJECTIVE
A3: This project evaluates whether opening a new Dollar General store meets the company's capital investment criteria. It replicates the type of analysis a corporate FP&A team would perform before approving real estate capex — building a 5-year pro-forma P&L, calculating NPV and IRR against a hurdle rate, and stress-testing assumptions across bear, base, and bull scenarios.
A5: WHY DOLLAR GENERAL?
A6: Dollar General is the most aggressive store opener in US retail — 730 new stores in FY2024 alone. Every single one of those openings requires a capital investment decision supported by exactly this type of pro-forma analysis. The company's 10-K provides transparent store-level metrics (revenue per sq ft, margins, capex disclosures) that make the model anchored in real, auditable data.
A8: DATA SOURCES
A9: - Dollar General 10-K FY2024 (SEC EDGAR): gross margin %, SG&A %, store sq footage, revenue per sq ft ($259)
A10: - Dollar General Q3 FY2024 Earnings Release: store-facility capex $259M / 730 new stores => ~$355K per store
A11: - Dollar General Q4 FY2024 Earnings Release: same-store sales comps guidance, tax rate (21.8%)
A12: - Industry standard: NNN lease costs, pre-opening expenses, initial inventory investment
A14: MODEL STRUCTURE
A15: Sheet 1 – Assumptions: All model inputs in one place. Change any blue cell to update the full model.
... A29: Prepared by: Anagha Athreyas | MS Finance (STEM), Northeastern University | github.com/AnaghaAthreyas
